{
  "pollutant": "no2",
  "origin": {
    "address": "Estadi Olimpic, Barcelona",
    "coordinates": [
      41.366095,
      2.1553243
    ]
  },
  "destination": {
    "address": "Recinte Modernista, Barcelona",
    "coordinates": [
      41.41266535,
      2.174335853538536
    ]
  },
  "shortest": {
    "route": [
      [
        2.1554117,
        41.3661001
      ],
      [
        2.1554022,
        41.3661954
      ],
      [
        2.1559507,
        41.3662668
      ],
      [
        2.1569394,
        41.3665083
      ],
      [
        2.1573648,
        41.3669434
      ],
      [
        2.1574227,
        41.3669435
      ],
      [
        2.1574242,
        41.366985
      ],
      [
        2.1576409,
        41.3671289
      ],
      [
        2.1577878,
        41.3672644
      ],
      [
        2.1578657,
        41.3673161
      ],
      [
        2.1579098,
        41.3673446
      ],
      [
        2.1581134,
        41.3674925
      ],
      [
        2.1581691,
        41.3675395
      ],
      [
        2.1582364,
        41.3675621
      ],
      [
        2.1582288,
        41.3675792
      ],
      [
        2.1583848,
        41.3676847
      ],
      [
        2.1583323,
        41.3677208
      ],
      [
        2.1582892,
        41.3678128
      ],
      [
        2.158344,
        41.3680638
      ],
      [
        2.1583929,
        41.3681929
      ],
      [
        2.158115,
        41.3681593
      ],
      [
        2.1582907,
        41.3685008
      ],
      [
        2.1583661,
        41.3686644
      ],
      [
        2.1583089,
        41.3687027
      ],
      [
        2.1583563,
        41.3692419
      ],
      [
        2.1583599,
        41.3694684
      ],
      [
        2.1585524,
        41.3701942
      ],
      [
        2.1589181,
        41.3707115
      ],
      [
        2.1591645,
        41.3708814
      ],
      [
        2.1595775,
        41.3711533
      ],
      [
        2.1597026,
        41.3712011
      ],
      [
        2.1597455,
        41.3712175
      ],
      [
        2.1598092,
        41.3712492
      ],
      [
        2.1597892,
        41.3713114
      ],
      [
        2.1600779,
        41.3713949
      ],
      [
        2.1601936,
        41.3714283
      ],
      [
        2.1601967,
        41.3714977
      ],
      [
        2.1603613,
        41.3720793
      ],
      [
        2.1603748,
        41.372127
      ],
      [
        2.1604486,
        41.3722856
      ],
      [
        2.1605843,
        41.3726926
      ],
      [
        2.1605974,
        41.3727257
      ],
      [
        2.1606142,
        41.3727705
      ],
      [
        2.1610108,
        41.3738451
      ],
      [
        2.161021,
        41.3738754
      ],
      [
        2.1610308,
        41.373907
      ],
      [
        2.1612597,
        41.3745869
      ],
      [
        2.1614668,
        41.3748466
      ],
      [
        2.1612812,
        41.3748502
      ],
      [
        2.1611274,
        41.3748532
      ],
      [
        2.1611245,
        41.3749259
      ],
      [
        2.1611196,
        41.3750497
      ],
      [
        2.1611162,
        41.3751372
      ],
      [
        2.1611332,
        41.375325
      ],
      [
        2.1610917,
        41.3753518
      ],
      [
        2.1610513,
        41.3753778
      ],
      [
        2.1617911,
        41.375971
      ],
      [
        2.1618004,
        41.3762151
      ],
      [
        2.1618695,
        41.3762558
      ],
      [
        2.1619172,
        41.3762847
      ],
      [
        2.1612101,
        41.3768181
      ],
      [
        2.1612114,
        41.3770661
      ],
      [
        2.1611563,
        41.3771133
      ],
      [
        2.1611094,
        41.3771573
      ],
      [
        2.1619504,
        41.3777887
      ],
      [
        2.1619989,
        41.3778209
      ],
      [
        2.1620307,
        41.3778419
      ],
      [
        2.1621756,
        41.3779596
      ],
      [
        2.1622463,
        41.3780123
      ],
      [
        2.1628909,
        41.3784969
      ],
      [
        2.1629122,
        41.3787125
      ],
      [
        2.162954,
        41.3788292
      ],
      [
        2.1629936,
        41.3789238
      ],
      [
        2.1629739,
        41.3790041
      ],
      [
        2.1631492,
        41.3801365
      ],
      [
        2.1631594,
        41.3802079
      ],
      [
        2.1631744,
        41.3803124
      ],
      [
        2.1631749,
        41.3803587
      ],
      [
        2.1631758,
        41.380439
      ],
      [
        2.1631765,
        41.3804588
      ],
      [
        2.1631794,
        41.3805386
      ],
      [
        2.1632039,
        41.3806867
      ],
      [
        2.1633884,
        41.3818283
      ],
      [
        2.1633973,
        41.381901
      ],
      [
        2.1634044,
        41.3819561
      ],
      [
        2.1634188,
        41.3820829
      ],
      [
        2.1634267,
        41.3821895
      ],
      [
        2.1636068,
        41.3823278
      ],
      [
        2.163631,
        41.3825236
      ],
      [
        2.163727,
        41.3832984
      ],
      [
        2.1637323,
        41.3833414
      ],
      [
        2.1638149,
        41.3840063
      ],
      [
        2.1638315,
        41.3841429
      ],
      [
        2.1638444,
        41.3842301
      ],
      [
        2.1639291,
        41.3849124
      ],
      [
        2.1639634,
        41.3851732
      ],
      [
        2.1639724,
        41.3852581
      ],
      [
        2.1640138,
        41.385401
      ],
      [
        2.1644843,
        41.3858005
      ],
      [
        2.1643818,
        41.3858746
      ],
      [
        2.1642934,
        41.385936
      ],
      [
        2.1641878,
        41.3860094
      ],
      [
        2.164148,
        41.3860528
      ],
      [
        2.1643098,
        41.386174
      ],
      [
        2.1644249,
        41.3862669
      ],
      [
        2.1653474,
        41.3869702
      ],
      [
        2.1655422,
        41.3871122
      ],
      [
        2.1657668,
        41.3872927
      ],
      [
        2.1657178,
        41.3873782
      ],
      [
        2.1668189,
        41.3882282
      ],
      [
        2.1667365,
        41.3882883
      ],
      [
        2.166859,
        41.3884665
      ],
      [
        2.1669951,
        41.388609
      ],
      [
        2.1671442,
        41.388734
      ],
      [
        2.1678885,
        41.3892894
      ],
      [
        2.1680684,
        41.3894252
      ],
      [
        2.1680307,
        41.3894808
      ],
      [
        2.1682542,
        41.3896564
      ],
      [
        2.1684417,
        41.3897975
      ],
      [
        2.1695703,
        41.3906431
      ],
      [
        2.1697139,
        41.3907456
      ],
      [
        2.1698777,
        41.3908739
      ],
      [
        2.17063,
        41.3914472
      ],
      [
        2.1705963,
        41.3914725
      ],
      [
        2.1707146,
        41.3916413
      ],
      [
        2.1707702,
        41.3916812
      ],
      [
        2.1699744,
        41.3922857
      ],
      [
        2.1700186,
        41.3923105
      ],
      [
        2.170059,
        41.3925645
      ],
      [
        2.1707245,
        41.3930705
      ],
      [
        2.1706579,
        41.3931239
      ],
      [
        2.1707002,
        41.3931549
      ],
      [
        2.1708871,
        41.3932917
      ],
      [
        2.1711052,
        41.3934579
      ],
      [
        2.1717916,
        41.3939861
      ],
      [
        2.171857,
        41.3940312
      ],
      [
        2.1720246,
        41.3941501
      ],
      [
        2.1722111,
        41.3942882
      ],
      [
        2.1722433,
        41.394312
      ],
      [
        2.1721894,
        41.3943509
      ],
      [
        2.1729026,
        41.3948896
      ],
      [
        2.1728886,
        41.3951042
      ],
      [
        2.1722043,
        41.3956619
      ],
      [
        2.1722622,
        41.3957042
      ],
      [
        2.172312,
        41.3957345
      ],
      [
        2.1722296,
        41.3957974
      ],
      [
        2.1722191,
        41.3959895
      ],
      [
        2.1729678,
        41.3965536
      ],
      [
        2.1731158,
        41.3966651
      ],
      [
        2.1732084,
        41.3967429
      ],
      [
        2.1740314,
        41.3973536
      ],
      [
        2.1739946,
        41.3973798
      ],
      [
        2.1740225,
        41.3976765
      ],
      [
        2.1733805,
        41.3981696
      ],
      [
        2.1734244,
        41.3982035
      ],
      [
        2.1734878,
        41.398248
      ],
      [
        2.1734973,
        41.3984774
      ],
      [
        2.1738828,
        41.3987836
      ],
      [
        2.1741787,
        41.3990185
      ],
      [
        2.1739949,
        41.3991614
      ],
      [
        2.1740035,
        41.3994064
      ],
      [
        2.1740377,
        41.3994283
      ],
      [
        2.1740967,
        41.3994754
      ],
      [
        2.1736936,
        41.3998531
      ],
      [
        2.1736439,
        41.3999208
      ],
      [
        2.1735766,
        41.400163
      ],
      [
        2.1735617,
        41.4002528
      ],
      [
        2.1735157,
        41.4002715
      ],
      [
        2.1734652,
        41.4003002
      ],
      [
        2.1741044,
        41.4008044
      ],
      [
        2.1740349,
        41.4008598
      ],
      [
        2.1740383,
        41.401058
      ],
      [
        2.1736251,
        41.4013626
      ],
      [
        2.1733365,
        41.4015953
      ],
      [
        2.1734046,
        41.4016509
      ],
      [
        2.1734523,
        41.4016898
      ],
      [
        2.1734947,
        41.401933
      ],
      [
        2.1734169,
        41.4019861
      ],
      [
        2.1733394,
        41.4020425
      ],
      [
        2.1735672,
        41.4022121
      ],
      [
        2.1734853,
        41.4026677
      ],
      [
        2.1736054,
        41.4030698
      ],
      [
        2.1736178,
        41.403088
      ],
      [
        2.1733264,
        41.4033095
      ],
      [
        2.1733759,
        41.4033474
      ],
      [
        2.1734341,
        41.4033919
      ],
      [
        2.1734418,
        41.4034275
      ],
      [
        2.1734585,
        41.4036345
      ],
      [
        2.1735307,
        41.4036904
      ],
      [
        2.1743758,
        41.4043097
      ],
      [
        2.1743186,
        41.404357
      ],
      [
        2.1744804,
        41.40447
      ],
      [
        2.1743448,
        41.4045643
      ],
      [
        2.1743618,
        41.4046721
      ],
      [
        2.1743594,
        41.4047829
      ],
      [
        2.1743357,
        41.4058583
      ],
      [
        2.1742963,
        41.4058552
      ],
      [
        2.1742446,
        41.4059463
      ],
      [
        2.1741794,
        41.40599
      ],
      [
        2.1741338,
        41.4060298
      ],
      [
        2.1741388,
        41.4062885
      ],
      [
        2.1741919,
        41.4063277
      ],
      [
        2.1742403,
        41.4063659
      ],
      [
        2.1742955,
        41.406428
      ],
      [
        2.1743305,
        41.4064331
      ],
      [
        2.1742933,
        41.4075827
      ],
      [
        2.1742878,
        41.4077551
      ],
      [
        2.1743114,
        41.4078642
      ],
      [
        2.1743092,
        41.4080864
      ],
      [
        2.1742675,
        41.4080852
      ],
      [
        2.1742439,
        41.4092646
      ],
      [
        2.1741596,
        41.4092681
      ],
      [
        2.1741427,
        41.4092947
      ],
      [
        2.1740577,
        41.4093793
      ],
      [
        2.1740797,
        41.4096395
      ],
      [
        2.174123,
        41.4096594
      ],
      [
        2.1742191,
        41.4097356
      ],
      [
        2.1742456,
        41.4097498
      ],
      [
        2.174284,
        41.4097584
      ],
      [
        2.1742348,
        41.4108983
      ],
      [
        2.1742258,
        41.4111056
      ],
      [
        2.1743107,
        41.4111789
      ],
      [
        2.1745424,
        41.411354
      ],
      [
        2.1749158,
        41.411634
      ],
      [
        2.1752126,
        41.4118573
      ],
      [
        2.1751499,
        41.4118969
      ],
      [
        2.1756183,
        41.4122462
      ],
      [
        2.1763325,
        41.4127805
      ],
      [
        2.1760842,
        41.4129682
      ],
      [
        2.1753877,
        41.4138321
      ],
      [
        2.1752876,
        41.4139278
      ],
      [
        2.1741906,
        41.4140444
      ],
      [
        2.1737417,
        41.413976
      ],
      [
        2.173343,
        41.413968
      ],
      [
        2.1733028,
        41.4130065
      ]
    ],
    "distance": 6959.603,
    "exposure": 233843.27000000005
  },
  "historical": {
    "route": [
      [
        2.1554117,
        41.3661001
      ],
      [
        2.1559797,
        41.3661822
      ],
      [
        2.1563987,
        41.3662651
      ],
      [
        2.156773,
        41.3663643
      ],
      [
        2.1570114,
        41.3664402
      ],
      [
        2.1576407,
        41.3666679
      ],
      [
        2.1577755,
        41.3667236
      ],
      [
        2.1580507,
        41.3668464
      ],
      [
        2.1588527,
        41.3672815
      ],
      [
        2.159092,
        41.3674104
      ],
      [
        2.1592369,
        41.3674949
      ],
      [
        2.1602215,
        41.3681459
      ],
      [
        2.1601366,
        41.3682164
      ],
      [
        2.1607424,
        41.3685497
      ],
      [
        2.1619762,
        41.3689455
      ],
      [
        2.1619329,
        41.3690846
      ],
      [
        2.1618536,
        41.3691523
      ],
      [
        2.1617989,
        41.3702211
      ],
      [
        2.1625524,
        41.3707915
      ],
      [
        2.1626429,
        41.3710412
      ],
      [
        2.1626824,
        41.3710481
      ],
      [
        2.1628342,
        41.3713282
      ],
      [
        2.163379,
        41.3712452
      ],
      [
        2.1633795,
        41.3712859
      ],
      [
        2.1634477,
        41.3712781
      ],
      [
        2.1634902,
        41.3712687
      ],
      [
        2.1643789,
        41.3719017
      ],
      [
        2.1644191,
        41.3718913
      ],
      [
        2.1644306,
        41.3719144
      ],
      [
        2.1650219,
        41.3717912
      ],
      [
        2.165075,
        41.3717782
      ],
      [
        2.1651123,
        41.3717692
      ],
      [
        2.1655544,
        41.3716787
      ],
      [
        2.1655913,
        41.3716733
      ],
      [
        2.1656069,
        41.3716971
      ],
      [
        2.1659763,
        41.3722582
      ],
      [
        2.1664296,
        41.372955
      ],
      [
        2.1675942,
        41.3745411
      ],
      [
        2.1677196,
        41.3748214
      ],
      [
        2.1677403,
        41.3748983
      ],
      [
        2.1679046,
        41.3748999
      ],
      [
        2.1678828,
        41.3750375
      ],
      [
        2.167822,
        41.3751435
      ],
      [
        2.1677437,
        41.3752145
      ],
      [
        2.1685389,
        41.3758356
      ],
      [
        2.1685959,
        41.3758837
      ],
      [
        2.1687108,
        41.3759947
      ],
      [
        2.1691078,
        41.376374
      ],
      [
        2.1693222,
        41.3765308
      ],
      [
        2.169631,
        41.3767615
      ],
      [
        2.1699325,
        41.3770452
      ],
      [
        2.1699413,
        41.3770538
      ],
      [
        2.1699485,
        41.3770617
      ],
      [
        2.1703481,
        41.3775999
      ],
      [
        2.1704119,
        41.3776143
      ],
      [
        2.1704967,
        41.3776505
      ],
      [
        2.170565,
        41.3776978
      ],
      [
        2.1706168,
        41.3777483
      ],
      [
        2.1706438,
        41.3777955
      ],
      [
        2.1706731,
        41.3778467
      ],
      [
        2.1711038,
        41.378198
      ],
      [
        2.1711198,
        41.3782126
      ],
      [
        2.1711358,
        41.3782272
      ],
      [
        2.1715206,
        41.37858
      ],
      [
        2.1720842,
        41.379088
      ],
      [
        2.1721135,
        41.3791144
      ],
      [
        2.1721469,
        41.3791508
      ],
      [
        2.1722346,
        41.3792464
      ],
      [
        2.1728117,
        41.378978
      ],
      [
        2.1732552,
        41.3794255
      ],
      [
        2.1739404,
        41.3800859
      ],
      [
        2.1739615,
        41.3801373
      ],
      [
        2.1739918,
        41.3801547
      ],
      [
        2.1740956,
        41.3802111
      ],
      [
        2.1742088,
        41.3802599
      ],
      [
        2.1742375,
        41.3802727
      ],
      [
        2.1742259,
        41.3803579
      ],
      [
        2.1744828,
        41.3805687
      ],
      [
        2.1745719,
        41.3806403
      ],
      [
        2.17481,
        41.3808331
      ],
      [
        2.175155,
        41.3811079
      ],
      [
        2.1753493,
        41.3812572
      ],
      [
        2.1755659,
        41.3814305
      ],
      [
        2.1758448,
        41.3816613
      ],
      [
        2.1758524,
        41.3816674
      ],
      [
        2.1764674,
        41.3821508
      ],
      [
        2.176837,
        41.3824493
      ],
      [
        2.1772301,
        41.382766
      ],
      [
        2.1773603,
        41.3828765
      ],
      [
        2.1776034,
        41.3830516
      ],
      [
        2.1776138,
        41.3830594
      ],
      [
        2.177971,
        41.3833283
      ],
      [
        2.1779851,
        41.3833399
      ],
      [
        2.1781474,
        41.3834736
      ],
      [
        2.1784466,
        41.3837272
      ],
      [
        2.178506,
        41.3837763
      ],
      [
        2.1786341,
        41.3838865
      ],
      [
        2.178734,
        41.3839602
      ],
      [
        2.178821,
        41.3840291
      ],
      [
        2.1791912,
        41.3843226
      ],
      [
        2.1792427,
        41.3843632
      ],
      [
        2.1793314,
        41.3844314
      ],
      [
        2.1794133,
        41.3844962
      ],
      [
        2.1796196,
        41.3846606
      ],
      [
        2.1797152,
        41.3847374
      ],
      [
        2.1797269,
        41.3847471
      ],
      [
        2.1805025,
        41.3853677
      ],
      [
        2.1805177,
        41.3853799
      ],
      [
        2.1812389,
        41.3859571
      ],
      [
        2.1812512,
        41.3859669
      ],
      [
        2.1815491,
        41.3862033
      ],
      [
        2.181557,
        41.3862088
      ],
      [
        2.1816265,
        41.386257
      ],
      [
        2.1818201,
        41.3864104
      ],
      [
        2.1818956,
        41.3864676
      ],
      [
        2.1820736,
        41.386603
      ],
      [
        2.1821657,
        41.386687
      ],
      [
        2.1820189,
        41.3869473
      ],
      [
        2.1817816,
        41.3876437
      ],
      [
        2.1818835,
        41.3877151
      ],
      [
        2.1822684,
        41.3880089
      ],
      [
        2.1822929,
        41.388052
      ],
      [
        2.1823795,
        41.3881285
      ],
      [
        2.1823969,
        41.3882027
      ],
      [
        2.1825363,
        41.3883033
      ],
      [
        2.1830192,
        41.3886707
      ],
      [
        2.1831047,
        41.3887312
      ],
      [
        2.1834113,
        41.3889553
      ],
      [
        2.1837253,
        41.3891871
      ],
      [
        2.1837977,
        41.3892477
      ],
      [
        2.1839032,
        41.3893281
      ],
      [
        2.1845158,
        41.3897947
      ],
      [
        2.1846398,
        41.3898868
      ],
      [
        2.1856637,
        41.3906538
      ],
      [
        2.1857777,
        41.3907367
      ],
      [
        2.1866325,
        41.3913862
      ],
      [
        2.1867524,
        41.391547
      ],
      [
        2.186795,
        41.3918677
      ],
      [
        2.187011,
        41.3918644
      ],
      [
        2.1870287,
        41.3927903
      ],
      [
        2.1870993,
        41.392787
      ],
      [
        2.1871031,
        41.3929562
      ],
      [
        2.1871008,
        41.3930728
      ],
      [
        2.1871036,
        41.3932508
      ],
      [
        2.1871058,
        41.3933571
      ],
      [
        2.1871059,
        41.3935229
      ],
      [
        2.1871068,
        41.3943424
      ],
      [
        2.1872109,
        41.3943267
      ],
      [
        2.1873184,
        41.394382
      ],
      [
        2.1873689,
        41.3944178
      ],
      [
        2.1873892,
        41.3944349
      ],
      [
        2.1874278,
        41.3944649
      ],
      [
        2.1875369,
        41.3945514
      ],
      [
        2.1872871,
        41.3949665
      ],
      [
        2.1872604,
        41.3950294
      ],
      [
        2.1872253,
        41.3951122
      ],
      [
        2.187131,
        41.3951513
      ],
      [
        2.1871301,
        41.3952229
      ],
      [
        2.1872118,
        41.3962503
      ],
      [
        2.1872912,
        41.3962979
      ],
      [
        2.1873458,
        41.3963353
      ],
      [
        2.1873679,
        41.3966876
      ],
      [
        2.1879423,
        41.3970941
      ],
      [
        2.1878958,
        41.3971456
      ],
      [
        2.1878484,
        41.3971857
      ],
      [
        2.1879756,
        41.3973202
      ],
      [
        2.1880302,
        41.3973493
      ],
      [
        2.1881193,
        41.39741
      ],
      [
        2.1882333,
        41.3974915
      ],
      [
        2.18837,
        41.397594
      ],
      [
        2.1882908,
        41.3977784
      ],
      [
        2.1880693,
        41.3987499
      ],
      [
        2.1881983,
        41.3988673
      ],
      [
        2.1882863,
        41.3988639
      ],
      [
        2.1883517,
        41.3989073
      ],
      [
        2.1884196,
        41.398963
      ],
      [
        2.1884333,
        41.3991564
      ],
      [
        2.1885586,
        41.3992544
      ],
      [
        2.1891247,
        41.3996687
      ],
      [
        2.189055,
        41.3997191
      ],
      [
        2.1892465,
        41.3998614
      ],
      [
        2.1891869,
        41.3999212
      ],
      [
        2.188326,
        41.4005683
      ],
      [
        2.1883776,
        41.4006061
      ],
      [
        2.188451,
        41.4006612
      ],
      [
        2.1884638,
        41.4008749
      ],
      [
        2.1884186,
        41.4009075
      ],
      [
        2.1892169,
        41.401516
      ],
      [
        2.1892964,
        41.4015694
      ],
      [
        2.1893741,
        41.4016282
      ],
      [
        2.1902481,
        41.4022947
      ],
      [
        2.1902197,
        41.4023262
      ],
      [
        2.1901986,
        41.4025299
      ],
      [
        2.1902595,
        41.4025689
      ],
      [
        2.1898698,
        41.4028678
      ],
      [
        2.1898379,
        41.4028923
      ],
      [
        2.1898065,
        41.4029164
      ],
      [
        2.1897709,
        41.4029436
      ],
      [
        2.1897278,
        41.4029767
      ],
      [
        2.1890254,
        41.4035116
      ],
      [
        2.1889136,
        41.4035966
      ],
      [
        2.1885484,
        41.4038684
      ],
      [
        2.1882444,
        41.4040992
      ],
      [
        2.1880712,
        41.404231
      ],
      [
        2.1878865,
        41.4043708
      ],
      [
        2.1874868,
        41.4046729
      ],
      [
        2.1871552,
        41.404925
      ],
      [
        2.1870613,
        41.4049971
      ],
      [
        2.1868469,
        41.4051598
      ],
      [
        2.1867577,
        41.4052276
      ],
      [
        2.1867235,
        41.4052535
      ],
      [
        2.1864392,
        41.4054693
      ],
      [
        2.1858561,
        41.4059044
      ],
      [
        2.1856666,
        41.406047
      ],
      [
        2.1854538,
        41.4062119
      ],
      [
        2.1847536,
        41.4067456
      ],
      [
        2.1845323,
        41.4069142
      ],
      [
        2.1843224,
        41.4070749
      ],
      [
        2.1840985,
        41.4072464
      ],
      [
        2.1839877,
        41.4073312
      ],
      [
        2.1839004,
        41.4073979
      ],
      [
        2.1836186,
        41.4076132
      ],
      [
        2.1834594,
        41.4077349
      ],
      [
        2.1832001,
        41.407932
      ],
      [
        2.1828788,
        41.4081761
      ],
      [
        2.1824703,
        41.4084751
      ],
      [
        2.1822831,
        41.4086115
      ],
      [
        2.1820767,
        41.4087743
      ],
      [
        2.1814541,
        41.4092589
      ],
      [
        2.1812185,
        41.4094379
      ],
      [
        2.1810107,
        41.4096025
      ],
      [
        2.1803032,
        41.4101356
      ],
      [
        2.1800942,
        41.410293
      ],
      [
        2.1797652,
        41.4105419
      ],
      [
        2.1796897,
        41.410599
      ],
      [
        2.1795748,
        41.4106834
      ],
      [
        2.1790908,
        41.4110387
      ],
      [
        2.1788596,
        41.4112065
      ],
      [
        2.1786614,
        41.4113743
      ],
      [
        2.1783341,
        41.41164
      ],
      [
        2.1779444,
        41.411926
      ],
      [
        2.1777352,
        41.4120801
      ],
      [
        2.177505,
        41.4122453
      ],
      [
        2.1771936,
        41.4124687
      ],
      [
        2.1768325,
        41.4127466
      ],
      [
        2.1766289,
        41.4129033
      ],
      [
        2.17656,
        41.4128526
      ],
      [
        2.1764917,
        41.4129024
      ],
      [
        2.176471,
        41.4129175
      ],
      [
        2.1762854,
        41.4130527
      ],
      [
        2.1762838,
        41.4138392
      ],
      [
        2.1753877,
        41.4138321
      ],
      [
        2.1752876,
        41.4139278
      ],
      [
        2.1741906,
        41.4140444
      ],
      [
        2.1737417,
        41.413976
      ],
      [
        2.173343,
        41.413968
      ],
      [
        2.1733028,
        41.4130065
      ]
    ],
    "distance": 7891.672000000002,
    "exposure": 197208.77000000008
  }
}